cmdserver/VERSION
cmdserver/__init__.py
cmdserver/apis/__init__.py
cmdserver/apis/command.py
cmdserver/apis/commands.py
cmdserver/apis/info.py
cmdserver/apis/pj.py
cmdserver/apis/version.py
cmdserver/commandcontroller.py
cmdserver/config.py
cmdserver/debounce.py
cmdserver/jvc.py
cmdserver/jvccommands.py
cmdserver/main.py
cmdserver/mqtt.py
cmdserver/pjcontroller.py
cmdserver/ws.py
ezmote_cmdserver-2.0.5.dist-info/LICENSE
ezmote_cmdserver-2.0.5.dist-info/METADATA
ezmote_cmdserver-2.0.5.dist-info/WHEEL
ezmote_cmdserver-2.0.5.dist-info/entry_points.txt
ezmote_cmdserver-2.0.5.dist-info/RECORD
