Metadata-Version: 2.3
Name: ezmote-cmdserver
Version: 2.0.5
Summary: A small webapp which can be used for web based home cinema automation
License: MIT
Author: 3ll3d00d
Author-email: mattkhan+cmdserver@gmail.com
Requires-Python: >=3.13, <3.14
Classifier: License :: OSI Approved :: MIT License
Classifier: Programming Language :: Python :: 3
Classifier: Programming Language :: Python :: 3.13
Requires-Dist: Werkzeug (>=2.0.0,<3.0)
Requires-Dist: autobahn[twisted] (>=24.4.2,<25.0)
Requires-Dist: flask (>=2.3.3,<3.0)
Requires-Dist: flask-restx (>=1.3.0,<2.0.0)
Requires-Dist: paho-mqtt (>=1.6.1,<2.0)
Requires-Dist: plumbum (>=1.9.0,<2.0)
Requires-Dist: pyyaml (>=6.0.2,<7.0)
Requires-Dist: requests (>=2.32.3,<3.0)
